CONTRIBUTING.md
MANIFEST.in
README.md
ongair-cli
ongair-health-cli
ongair-monitor-cli
requirements.txt
setup.cfg
setup.py
ongair/__init__.py
ongair/client.py
ongair/exception.py
ongair/models.py
ongair/ongair.py
ongair/util.py
ongair_whatsapp.egg-info/PKG-INFO
ongair_whatsapp.egg-info/SOURCES.txt
ongair_whatsapp.egg-info/dependency_links.txt
ongair_whatsapp.egg-info/requires.txt
ongair_whatsapp.egg-info/top_level.txt