Metadata-Version: 1.1
Name: ongair-whatsapp
Version: 1.0.37
Summary: Ongair layer that connects to whatsapp
Home-page: https://github.com/ongair/ongair-whatsapp
Author: Ongair Limited
Author-email: trevor@ongair.im
License: GPL
Platform: MacOS X
Platform: Windows
Platform: Linux
Classifier: License :: OSI Approved :: GNU General Public License (GPL)
Classifier: Development Status :: 5 - Production/Stable
Classifier: Natural Language :: English
Classifier: Programming Language :: Python
Classifier: Operating System :: OS Independent
Classifier: Programming Language :: Python :: Implementation :: PyPy
Classifier: Environment :: Console
Classifier: Topic :: Software Development :: Libraries :: Python Modules
Classifier: Intended Audience :: Developers
Classifier: Operating System :: POSIX :: Linux
Classifier: Operating System :: MacOS :: MacOS X
Classifier: Operating System :: Microsoft :: Windows
